chunk_nordic/__init__.py
chunk_nordic/asdnotify.py
chunk_nordic/client.py
chunk_nordic/combiner.py
chunk_nordic/constants.py
chunk_nordic/server.py
chunk_nordic/splitter.py
chunk_nordic/utils.py
chunk_nordic-0.4.2.dist-info/LICENSE
chunk_nordic-0.4.2.dist-info/METADATA
chunk_nordic-0.4.2.dist-info/WHEEL
chunk_nordic-0.4.2.dist-info/entry_points.txt
chunk_nordic-0.4.2.dist-info/top_level.txt
chunk_nordic-0.4.2.dist-info/zip-safe
chunk_nordic-0.4.2.dist-info/RECORD
