Metadata-Version: 2.1
Name: chunk-nordic
Version: 0.4.2
Summary: Yet another TCP-over-HTTP(S) tunnel
Home-page: https://github.com/Snawoot/chunk-nordic
Author: Vladislav Yarmak
Author-email: vladislav-ex-src@vm-0.com
License: MIT
Classifier: Programming Language :: Python :: 3.5
Classifier: License :: OSI Approved :: MIT License
Classifier: Operating System :: OS Independent
Classifier: Development Status :: 4 - Beta
Classifier: Environment :: No Input/Output (Daemon)
Classifier: Intended Audience :: System Administrators
Classifier: Natural Language :: English
Classifier: Topic :: Internet
Classifier: Topic :: Security
Requires-Python: >=3.5.3
License-File: LICENSE
Requires-Dist: aiohttp (>=3.4.4)
Provides-Extra: dev
Requires-Dist: pytest (>=3.0.0) ; extra == 'dev'
Requires-Dist: pytest-cov ; extra == 'dev'
Requires-Dist: pytest-asyncio ; extra == 'dev'
Requires-Dist: pytest-timeout ; extra == 'dev'
Requires-Dist: pylint ; extra == 'dev'
Requires-Dist: tox ; extra == 'dev'
Requires-Dist: coverage ; extra == 'dev'
Requires-Dist: setuptools (>=38.6.0) ; extra == 'dev'
Requires-Dist: wheel (>=0.31.0) ; extra == 'dev'
Requires-Dist: twine (>=1.11.0) ; extra == 'dev'
Requires-Dist: cryptography (>=1.6) ; extra == 'dev'
Provides-Extra: uvloop
Requires-Dist: uvloop (>=0.11.0) ; extra == 'uvloop'
